stego_client/__init__.py
stego_client/client.py
stego_client-0.1.0.dist-info/METADATA
stego_client-0.1.0.dist-info/WHEEL
stego_client-0.1.0.dist-info/top_level.txt
stego_client-0.1.0.dist-info/RECORD
