Metadata-Version: 2.4
Name: stego-client
Version: 0.1.0
Summary: Tiny client for LLM stego encode/decode over Modal
Author: Your Name
Project-URL: Homepage, https://github.com/youruser/stego-client
Requires-Python: >=3.8
Requires-Dist: requests>=2.0
